{
  "kind": "collectionType",
  "collectionName": "articles",
  "info": {
    "singularName": "article",
    "pluralName": "articles",
    "displayName": "Article"
  },
  "options": {
    "draftAndPublish": true
  },
  "pluginOptions": {},
  "attributes": {
    "articleTitle": {
      "type": "string"
    },
    "slug": {
      "type": "uid",
      "targetField": "articleTitle",
      "required": true
    },
    "category": {
      "type": "enumeration",
      "required": true,
      "enum": [
        "Books",
        "Culture",
        "Film + TV"
      ]
    },
    "articleType": {
      "type": "enumeration",
      "required": true,
      "enum": [
        "Recommendation List",
        "Long Post",
        "Review Post"
      ]
    },
    "shortDescription": {
      "type": "string"
    },
    "thumbnail": {
      "type": "media",
      "multiple": false,
      "allowedTypes": [
        "images",
        "files",
        "videos",
        "audios"
      ]
    },
    "coverImage": {
      "type": "media",
      "multiple": false,
      "allowedTypes": [
        "images",
        "files",
        "videos",
        "audios"
      ]
    },
    "excerpt": {
      "type": "text",
      "required": true
    },
    "isFeaturedPost": {
      "type": "boolean",
      "default": false
    },
    "genres": {
      "type": "relation",
      "relation": "oneToMany",
      "target": "api::genre.genre",
      "mappedBy": "article"
    },
    "availableOn": {
      "type": "component",
      "conditions": {
        "visible": {
          "==": [
            {
              "var": "articleType"
            },
            "Review Post"
          ]
        }
      },
      "component": "element.available-on",
      "repeatable": true
    },
    "review": {
      "type": "component",
      "conditions": {
        "visible": {
          "==": [
            {
              "var": "articleType"
            },
            "Review Post"
          ]
        }
      },
      "component": "element.review",
      "repeatable": false
    },
    "recommendationList": {
      "type": "component",
      "conditions": {
        "visible": {
          "==": [
            {
              "var": "articleType"
            },
            "Recommendation List"
          ]
        }
      },
      "component": "element.film-tv-books-list",
      "repeatable": true
    },
    "content": {
      "type": "blocks",
      "conditions": {
        "visible": {
          "==": [
            {
              "var": "articleType"
            },
            "Long Post"
          ]
        }
      }
    },
    "addToWatchlist": {
      "type": "enumeration",
      "enum": [
        "Yes",
        "No"
      ]
    },
    "author": {
      "type": "relation",
      "relation": "manyToOne",
      "target": "api::author.author",
      "inversedBy": "articles"
    },
    "tags": {
      "type": "relation",
      "relation": "manyToMany",
      "target": "api::tag.tag",
      "inversedBy": "articles"
    },
    "trailerLink": {
      "type": "string",
      "conditions": {
        "visible": {
          "==": [
            {
              "var": "articleType"
            },
            "Review Post"
          ]
        }
      }
    }
  }
}
